{
  "timestamp": "2026-04-02T09:56:03.285960+00:00",
  "pipeline_version": "1.0.0",
  "total_iterations": 1,
  "pipeline_duration_seconds": 11.27,
  "summary": {
    "initial_passed": 3063,
    "initial_failed": 0,
    "final_passed": 3063,
    "final_failed": 0,
    "total_improvements_applied": 0,
    "improvement_rate": "0.0%"
  },
  "iterations": [
    {
      "iteration": 1,
      "passed": 3063,
      "failed": 0,
      "errors": 0,
      "skipped": 10,
      "xfailed": 36,
      "total": 3109,
      "duration_seconds": 11.27,
      "failures": [],
      "improvements": []
    }
  ],
  "failure_categories": {}
}